{
  "MOVEMENT_GROUPS": {
    "HOME": {
      "velocity": 30,
      "acceleration": 40,
      "iterations": 1,
      "has_iterations": false,
      "has_trajectory_execution": true,
      "position": "[142.929, 280.025, 316.323, -0.081, -0.223, -11.314]"
    },
    "CALIBRATION": {
      "velocity": 10,
      "acceleration": 10,
      "iterations": 1,
      "has_iterations": false,
      "has_trajectory_execution": true,
      "position": "[337.874, -66.989, 544.004, -0.145, -0.067, -0.022]"
    },
    "CAMERA_CALIBRATION": {
      "velocity": 10,
      "acceleration": 10,
      "iterations": 1,
      "has_iterations": false,
      "has_trajectory_execution": true,
      "position": "[337.863, -66.989, 394.023, -0.151, -0.072, -0.015]"
    },
    "JOG": {
      "velocity": 0,
      "acceleration": 0,
      "iterations": 1,
      "has_iterations": false,
      "has_trajectory_execution": false
    },
    "PAINTING": {
      "velocity": 0,
      "acceleration": 0,
      "iterations": 1,
      "has_iterations": false,
      "has_trajectory_execution": true
    }
  }
}